README.md
setup.py
aliyun_console_bench_python_sdk.egg-info/PKG-INFO
aliyun_console_bench_python_sdk.egg-info/SOURCES.txt
aliyun_console_bench_python_sdk.egg-info/dependency_links.txt
aliyun_console_bench_python_sdk.egg-info/requires.txt
aliyun_console_bench_python_sdk.egg-info/top_level.txt
one_sdk/__init__.py
one_sdk/client.py